lemon/__init__.py
lemon/_lemon.py
lemon/_lemon_utils.py
lemon/_matching_attribution_explanation.py
lemon/utils/__init__.py
lemon/utils/datasets/__init__.py
lemon/utils/datasets/_dataset.py
lemon/utils/datasets/_utils.py
lemon/utils/datasets/deepmatcher.py
lemon/utils/matchers/__init__.py
lemon/utils/matchers/_magellan.py
lemon/utils/matchers/_transformer_matcher.py
lemon_explain-0.1.1.dist-info/LICENSE
lemon_explain-0.1.1.dist-info/WHEEL
lemon_explain-0.1.1.dist-info/METADATA
lemon_explain-0.1.1.dist-info/RECORD
