Metadata-Version: 2.1
Name: lemon-explain
Version: 0.1.1
Summary: LEMON: Explainable Entity Matching
Home-page: https://github.com/NilsBarlaug/lemon
License: MIT
Author: Nils Barlaug
Author-email: nils.barlaug@gmail.com
Requires-Python: >=3.7,<4.0
Classifier: License :: OSI Approved :: MIT License
Classifier: Programming Language :: Python :: 3
Classifier: Programming Language :: Python :: 3.10
Classifier: Programming Language :: Python :: 3.7
Classifier: Programming Language :: Python :: 3.8
Classifier: Programming Language :: Python :: 3.9
Provides-Extra: all
Provides-Extra: matchers
Provides-Extra: storage
Requires-Dist: pandas (>=1,<2)
Requires-Dist: py-entitymatching (>=0.4.0,<0.5.0); extra == "matchers" or extra == "all"
Requires-Dist: pyarrow (>=5.0.0,<6.0.0); extra == "storage" or extra == "all"
Requires-Dist: scikit-learn (>=1.0,<2.0)
Requires-Dist: torch (>=1.9.1,<2.0.0); extra == "matchers" or extra == "all"
Requires-Dist: transformers (>=4.10.3,<5.0.0); extra == "matchers" or extra == "all"
Project-URL: Documentation, https://github.com/NilsBarlaug/lemon
Project-URL: Repository, https://github.com/NilsBarlaug/lemon
